solcix/__init__.py
solcix/__main__.py
solcix/compile/__init__.py
solcix/compile/solc.py
solcix/constant.py
solcix/datatypes/__init__.py
solcix/datatypes/datatypes.py
solcix/errors.py
solcix/installer.py
solcix/manage/__init__.py
solcix/manage/manage.py
solcix/resolver.py
solcix/utils.py
solcix-0.1.8.dist-info/LICENSE
solcix-0.1.8.dist-info/METADATA
solcix-0.1.8.dist-info/WHEEL
solcix-0.1.8.dist-info/entry_points.txt
solcix-0.1.8.dist-info/RECORD
