Metadata-Version: 2.1
Name: solcix
Version: 0.1.8
Summary: A Python wrapper for the Solidity compiler. Switch between versions, compile, and manage artifacts.
Author: alan890104
Author-email: alan890104@gmail.com
Requires-Python: >=3.8,<4.0
Classifier: Programming Language :: Python :: 3
Classifier: Programming Language :: Python :: 3.8
Classifier: Programming Language :: Python :: 3.9
Classifier: Programming Language :: Python :: 3.10
Classifier: Programming Language :: Python :: 3.11
Requires-Dist: cfgv (==3.3.1)
Requires-Dist: click (==8.1.3)
Requires-Dist: colorama (>=0.4.6,<0.5.0)
Requires-Dist: distlib (==0.3.6)
Requires-Dist: filelock (==3.10.7)
Requires-Dist: identify (==2.5.22)
Requires-Dist: joblib (==1.2.0)
Requires-Dist: mypy-extensions (==1.0.0)
Requires-Dist: nodeenv (==1.7.0)
Requires-Dist: packaging (==23.0)
Requires-Dist: pathspec (==0.11.1)
Requires-Dist: platformdirs (==3.2.0)
Requires-Dist: pycryptodome (==3.17)
Requires-Dist: pyfiglet (>=0.8.post1,<0.9)
Requires-Dist: pyyaml (==6.0)
Requires-Dist: tomli (==2.0.1)
Requires-Dist: tqdm (==4.65.0)
Requires-Dist: virtualenv (==20.21.0)
